snazzy.py
snazzy-0.2.2.dist-info/LICENSE
snazzy-0.2.2.dist-info/METADATA
snazzy-0.2.2.dist-info/WHEEL
snazzy-0.2.2.dist-info/top_level.txt
snazzy-0.2.2.dist-info/RECORD
