Metadata-Version: 2.1
Name: snazzy
Version: 0.2.2
Summary: 'Stylish ANSI terminal colors and helpers'
Home-page: https://github.com/mar10/snazzy/
Author: Martin Wendt
Author-email: snazzy@wwwendt.de
Maintainer: Martin Wendt
Maintainer-email: snazzy@wwwendt.de
License: MIT
Keywords: terminal,console,ansi,escape
Platform: UNKNOWN
Classifier: Development Status :: 3 - Alpha
Classifier: Environment :: Console
Classifier: Intended Audience :: Developers
Classifier: License :: OSI Approved :: MIT License
Classifier: Operating System :: OS Independent
Classifier: Programming Language :: Python
Classifier: Programming Language :: Python :: 3
Classifier: Programming Language :: Python :: 3.5
Classifier: Programming Language :: Python :: 3.6
Classifier: Programming Language :: Python :: 3.7
Classifier: Programming Language :: Python :: 3.8
Classifier: Topic :: Software Development :: Build Tools
Classifier: Topic :: System :: Installation/Setup
Classifier: Topic :: System :: Software Distribution
